{
  "generated_at": "2026-03-25T12:00:00Z",
  "reports": [
    {
      "category": "Micro-SaaS",
      "title": "Webhook Reliability Platform for Indie Developers",
      "subtitle": "A focused workflow product for indie SaaS teams built to reduce manual coordination.",
      "report_path": "generated-reports/reports/webhook-reliability-platform-for-indie-developers.html",
      "overall_confidence": 86,
      "recommendation": "build"
    },
    {
      "category": "AI Automation",
      "title": "AI Output Validation for AI Product Teams",
      "subtitle": "A focused control layer for AI product teams that reduces the operational risk of AI output validation.",
      "report_path": "generated-reports/reports/ai-output-validation-for-ai-product-teams.html",
      "overall_confidence": 84,
      "recommendation": "build"
    },
    {
      "category": "Finance & Admin",
      "title": "Invoice Exception Review for Finance Teams",
      "subtitle": "A workflow product for finance teams built to reduce invoice errors and improve review discipline.",
      "report_path": "generated-reports/reports/invoice-exception-review-for-finance-teams.html",
      "overall_confidence": 81,
      "recommendation": "validate_first"
    },
    {
      "category": "Local Business",
      "title": "Patient Intake Follow-Up for Clinic Managers",
      "subtitle": "A practical operations layer for clinic managers built to reduce admin drag around patient intake follow-up.",
      "report_path": "generated-reports/reports/patient-intake-follow-up-for-clinic-managers.html",
      "overall_confidence": 79,
      "recommendation": "validate_first"
    },
    {
      "category": "B2B Services",
      "title": "Client Onboarding QA for AI Agencies",
      "subtitle": "A focused workflow product for AI agencies built to reduce messy onboarding.",
      "report_path": "generated-reports/reports/client-onboarding-qa-for-ai-agencies.html",
      "overall_confidence": 82,
      "recommendation": "build"
    }
  ]
}